sspo_client/__init__.py
sspo_client/api_client.py
sspo_client/configuration.py
sspo_client/rest.py
sspo_client/api/__init__.py
sspo_client/api/artifact_api.py
sspo_client/api/core_api.py
sspo_client/api/process_api.py
sspo_client/api/scrum_atomic_projects_api.py
sspo_client/api/scrum_complex_projects_api.py
sspo_client/api/scrum_projects_api.py
sspo_client/api/stakeholder_api.py
sspo_client/models/__init__.py
sspo_client/models/acceptance_criteria.py
sspo_client/models/acceptance_criteria_.py
sspo_client/models/application_.py
sspo_client/models/application_reference_.py
sspo_client/models/application_type_.py
sspo_client/models/atomic_user_story.py
sspo_client/models/atomic_user_story_.py
sspo_client/models/configuration_.py
sspo_client/models/developer_.py
sspo_client/models/developer_team_membership_.py
sspo_client/models/development_team.py
sspo_client/models/development_team_.py
sspo_client/models/epic.py
sspo_client/models/epic_.py
sspo_client/models/functional_acceptance_criteria.py
sspo_client/models/functional_acceptance_criteria_.py
sspo_client/models/non_functional_acceptance_criteria.py
sspo_client/models/non_functional_acceptance_criteria_.py
sspo_client/models/organization_.py
sspo_client/models/person.py
sspo_client/models/person_.py
sspo_client/models/product_backlog.py
sspo_client/models/product_backlog_.py
sspo_client/models/product_backlog_definition.py
sspo_client/models/product_backlog_definition_.py
sspo_client/models/product_owner_.py
sspo_client/models/product_owner_team_membership_.py
sspo_client/models/scrum_atomic_project.py
sspo_client/models/scrum_atomic_project_.py
sspo_client/models/scrum_complex_project.py
sspo_client/models/scrum_complex_project_.py
sspo_client/models/scrum_development_task.py
sspo_client/models/scrum_development_task_.py
sspo_client/models/scrum_intented_development_task.py
sspo_client/models/scrum_intented_development_task_.py
sspo_client/models/scrum_master_.py
sspo_client/models/scrum_master_team_membership_.py
sspo_client-1.1.11.dist-info/METADATA
sspo_client-1.1.11.dist-info/WHEEL
sspo_client-1.1.11.dist-info/top_level.txt
sspo_client-1.1.11.dist-info/RECORD
