Metadata-Version: 2.1
Name: sspo-client
Version: 1.1.11
Summary: SSPO Service
Home-page: UNKNOWN
Author: UNKNOWN
Author-email: UNKNOWN
License: UNKNOWN
Keywords: Swagger,SSPO Service
Platform: UNKNOWN
Requires-Dist: certifi (>=2017.4.17)
Requires-Dist: python-dateutil (>=2.1)
Requires-Dist: six (>=1.10)
Requires-Dist: urllib3 (>=1.23)
